awstwitter/__init__.py
awstwitter-1.0.3.dist-info/DESCRIPTION.rst
awstwitter-1.0.3.dist-info/METADATA
awstwitter-1.0.3.dist-info/RECORD
awstwitter-1.0.3.dist-info/WHEEL
awstwitter-1.0.3.dist-info/entry_points.txt
awstwitter-1.0.3.dist-info/metadata.json
awstwitter-1.0.3.dist-info/top_level.txt
