Metadata-Version: 2.0
Name: awstwitter
Version: 1.0.3
Summary: A Python module to make it easy to connect to twitter from AWS
Home-page: https://github.com/hsbakshi/awstwitter
Author: Hrishi Bakshi
Author-email: bakshi.hrishikesh@gmail.com
License: Apache License 2.0
Keywords: Allow AWS Serverless applications to connect to Twitter
Platform: UNKNOWN
Classifier: Development Status :: 4 - Beta
Classifier: Intended Audience :: Developers
Classifier: Topic :: Internet :: WWW/HTTP :: Indexing/Search
Classifier: License :: OSI Approved :: Apache Software License
Classifier: Programming Language :: Python :: 2
Classifier: Programming Language :: Python :: 2.7
Classifier: Programming Language :: Python :: 3
Classifier: Programming Language :: Python :: 3.3
Classifier: Programming Language :: Python :: 3.4
Classifier: Programming Language :: Python :: 3.5
Classifier: Programming Language :: Python :: 3.6
Requires-Dist: boto3
Provides-Extra: dev
Requires-Dist: check-manifest; extra == 'dev'
Provides-Extra: test
Requires-Dist: coverage; extra == 'test'
Requires-Dist: mock; extra == 'test'
Requires-Dist: nosetests; extra == 'test'
